databet/__init__.py
databet/_letters.py
databet/letters.py
databet/plotting.py
databet/stats.py
databet/version.py
databet-2023.1.2.dist-info/LICENSE
databet-2023.1.2.dist-info/METADATA
databet-2023.1.2.dist-info/WHEEL
databet-2023.1.2.dist-info/top_level.txt
databet-2023.1.2.dist-info/RECORD
