Metadata-Version: 2.1
Name: databet
Version: 2023.1.2
Summary: datasets with the same summary statistics that look like the alphabet
Home-page: https://github.com/mscroggs/databet
Author: Matthew Scroggs
Author-email: databet@mscroggs.co.uk
Maintainer-email: databet@mscroggs.co.uk
License: MIT
License-File: LICENSE
Requires-Dist: numpy
Requires-Dist: matplotlib
